treasuremap/__init__.py
treasuremap/apps.py
treasuremap/fields.py
treasuremap/forms.py
treasuremap/models.py
treasuremap/utils.py
treasuremap/widgets.py
treasuremap/backends/__init__.py
treasuremap/backends/base.py
treasuremap/backends/google.py
treasuremap/backends/yandex.py
treasuremap/static/treasuremap/default/js/jquery.treasuremap-google.js
treasuremap/static/treasuremap/default/js/jquery.treasuremap-yandex.js
treasuremap/templates/treasuremap/widgets/map.html
django_treasuremap-0.3.4.dist-info/LICENSE
django_treasuremap-0.3.4.dist-info/METADATA
django_treasuremap-0.3.4.dist-info/WHEEL
django_treasuremap-0.3.4.dist-info/top_level.txt
django_treasuremap-0.3.4.dist-info/RECORD
